{
  "race_id": "202403020701",
  "race_name": "",
  "date": "2024-07-20",
  "venue": "福島",
  "race_number": 1,
  "distance": 0,
  "surface": "",
  "track_direction": "",
  "weather": "",
  "condition": "",
  "year": "2024",
  "results": [
    {
      "rank": null,
      "gate_number": 1,
      "horse_number": 1,
      "horse_name": "クニノハッピー",
      "horse_id": "2022105990",
      "sex_age": "牡1",
      "weight_carried": 55.0,
      "jockey": "内田博幸",
      "trainer": "田中剛",
      "finish_time": null,
      "margin": null,
      "win_odds": null,
      "popularity": null,
      "horse_weight": null,
      "horse_weight_diff": null,
      "sire": null,
      "dam": null,
      "dam_sire": null
    },
    {
      "rank": null,
      "gate_number": 2,
      "horse_number": 2,
      "horse_name": "ビップジェシー",
      "horse_id": "2022103776",
      "sex_age": "牝3",
      "weight_carried": 55.0,
      "jockey": "菊沢一樹",
      "trainer": "田島俊明",
      "finish_time": null,
      "margin": null,
      "win_odds": null,
      "popularity": null,
      "horse_weight": null,
      "horse_weight_diff": null,
      "sire": null,
      "dam": null,
      "dam_sire": null
    },
    {
      "rank": null,
      "gate_number": 3,
      "horse_number": 3,
      "horse_name": "バム",
      "horse_id": "2022103327",
      "sex_age": "牡3",
      "weight_carried": 55.0,
      "jockey": "岩部純二",
      "trainer": "奥平雅士",
      "finish_time": null,
      "margin": null,
      "win_odds": null,
      "popularity": null,
      "horse_weight": null,
      "horse_weight_diff": null,
      "sire": null,
      "dam": null,
      "dam_sire": null
    },
    {
      "rank": null,
      "gate_number": 4,
      "horse_number": 4,
      "horse_name": "ブルーオブウインド",
      "horse_id": "2022106405",
      "sex_age": "牝4",
      "weight_carried": 55.0,
      "jockey": "吉田豊",
      "trainer": "的場均",
      "finish_time": null,
      "margin": null,
      "win_odds": null,
      "popularity": null,
      "horse_weight": null,
      "horse_weight_diff": null,
      "sire": null,
      "dam": null,
      "dam_sire": null
    },
    {
      "rank": null,
      "gate_number": 4,
      "horse_number": 5,
      "horse_name": "リトルサムシング",
      "horse_id": "2022105636",
      "sex_age": "牡4",
      "weight_carried": 55.0,
      "jockey": "戸崎圭太",
      "trainer": "野中賢二",
      "finish_time": null,
      "margin": null,
      "win_odds": null,
      "popularity": null,
      "horse_weight": null,
      "horse_weight_diff": null,
      "sire": null,
      "dam": null,
      "dam_sire": null
    },
    {
      "rank": null,
      "gate_number": 5,
      "horse_number": 6,
      "horse_name": "アニーブレイク",
      "horse_id": "2022103824",
      "sex_age": "牝3",
      "weight_carried": 51.0,
      "jockey": "大江原比",
      "trainer": "田島俊明",
      "finish_time": null,
      "margin": null,
      "win_odds": null,
      "popularity": null,
      "horse_weight": null,
      "horse_weight_diff": null,
      "sire": null,
      "dam": null,
      "dam_sire": null
    },
    {
      "rank": null,
      "gate_number": 5,
      "horse_number": 7,
      "horse_name": "ナックトライアンフ",
      "horse_id": "2022102362",
      "sex_age": "牡1",
      "weight_carried": 52.0,
      "jockey": "佐藤翔馬",
      "trainer": "杉浦宏昭",
      "finish_time": null,
      "margin": null,
      "win_odds": null,
      "popularity": null,
      "horse_weight": null,
      "horse_weight_diff": null,
      "sire": null,
      "dam": null,
      "dam_sire": null
    },
    {
      "rank": null,
      "gate_number": 6,
      "horse_number": 8,
      "horse_name": "リネンドライブ",
      "horse_id": "2022101185",
      "sex_age": "騸1",
      "weight_carried": 55.0,
      "jockey": "柴田大知",
      "trainer": "南田美知",
      "finish_time": null,
      "margin": null,
      "win_odds": null,
      "popularity": null,
      "horse_weight": null,
      "horse_weight_diff": null,
      "sire": null,
      "dam": null,
      "dam_sire": null
    },
    {
      "rank": null,
      "gate_number": 6,
      "horse_number": 9,
      "horse_name": "ニシノケンタマン",
      "horse_id": "2022106427",
      "sex_age": "牡5",
      "weight_carried": 55.0,
      "jockey": "野中悠太",
      "trainer": "深山雅史",
      "finish_time": null,
      "margin": null,
      "win_odds": null,
      "popularity": null,
      "horse_weight": null,
      "horse_weight_diff": null,
      "sire": null,
      "dam": null,
      "dam_sire": null
    },
    {
      "rank": null,
      "gate_number": 7,
      "horse_number": 10,
      "horse_name": "デルタウェーブ",
      "horse_id": "2022104146",
      "sex_age": "牝3",
      "weight_carried": 54.0,
      "jockey": "原優介",
      "trainer": "西園翔太",
      "finish_time": null,
      "margin": null,
      "win_odds": null,
      "popularity": null,
      "horse_weight": null,
      "horse_weight_diff": null,
      "sire": null,
      "dam": null,
      "dam_sire": null
    },
    {
      "rank": null,
      "gate_number": 7,
      "horse_number": 11,
      "horse_name": "カイトヴィント",
      "horse_id": "2022102991",
      "sex_age": "牡3",
      "weight_carried": 55.0,
      "jockey": "丸山元気",
      "trainer": "和田雄二",
      "finish_time": null,
      "margin": null,
      "win_odds": null,
      "popularity": null,
      "horse_weight": null,
      "horse_weight_diff": null,
      "sire": null,
      "dam": null,
      "dam_sire": null
    },
    {
      "rank": null,
      "gate_number": 8,
      "horse_number": 12,
      "horse_name": "アイビーヒメチャン",
      "horse_id": "2022103959",
      "sex_age": "牝3",
      "weight_carried": 55.0,
      "jockey": "木幡巧也",
      "trainer": "牧光二",
      "finish_time": null,
      "margin": null,
      "win_odds": null,
      "popularity": null,
      "horse_weight": null,
      "horse_weight_diff": null,
      "sire": null,
      "dam": null,
      "dam_sire": null
    },
    {
      "rank": null,
      "gate_number": 8,
      "horse_number": 13,
      "horse_name": "ダテヒリュウ",
      "horse_id": "2022100447",
      "sex_age": "牡4",
      "weight_carried": 55.0,
      "jockey": "石橋脩",
      "trainer": "西園正都",
      "finish_time": null,
      "margin": null,
      "win_odds": null,
      "popularity": null,
      "horse_weight": null,
      "horse_weight_diff": null,
      "sire": null,
      "dam": null,
      "dam_sire": null
    }
  ],
  "payouts": [],
  "predictions": [],
  "training_evals": {}
}