{
  "race_id": "202408010512",
  "race_name": "",
  "date": "2024-01-14",
  "venue": "京都",
  "race_number": 12,
  "distance": 0,
  "surface": "",
  "track_direction": "",
  "weather": "",
  "condition": "",
  "year": "2024",
  "results": [
    {
      "rank": 1,
      "gate_number": 1,
      "horse_number": 1,
      "horse_name": "オードリーバローズ",
      "horse_id": null,
      "sex_age": "牝4",
      "weight_carried": 55.0,
      "jockey": "松山",
      "trainer": "栗東清水久",
      "finish_time": "1:21.5",
      "margin": null,
      "win_odds": 5.1,
      "popularity": 3,
      "horse_weight": 476,
      "horse_weight_diff": -4,
      "sire": null,
      "dam": null,
      "dam_sire": null,
      "honmei_score": 0.0302,
      "ev_score": 0.0,
      "kelly_fraction": null,
      "manji_ev": null,
      "odds_vs_morning": null,
      "odds_velocity": null
    },
    {
      "rank": 2,
      "gate_number": 8,
      "horse_number": 10,
      "horse_name": "ケイデンシーマーク",
      "horse_id": null,
      "sex_age": "牝4",
      "weight_carried": 55.0,
      "jockey": "北村友",
      "trainer": "栗東安田隆",
      "finish_time": "1:21.5",
      "margin": "ハナ",
      "win_odds": 2.5,
      "popularity": 1,
      "horse_weight": 438,
      "horse_weight_diff": -2,
      "sire": null,
      "dam": null,
      "dam_sire": null,
      "honmei_score": 0.0772,
      "ev_score": 0.5347,
      "kelly_fraction": null,
      "manji_ev": null,
      "odds_vs_morning": null,
      "odds_velocity": null
    },
    {
      "rank": 3,
      "gate_number": 5,
      "horse_number": 5,
      "horse_name": "アロマデローサ",
      "horse_id": null,
      "sex_age": "牝4",
      "weight_carried": 55.0,
      "jockey": "西村淳",
      "trainer": "栗東池添",
      "finish_time": "1:21.6",
      "margin": "1",
      "win_odds": 3.7,
      "popularity": 2,
      "horse_weight": 448,
      "horse_weight_diff": 2,
      "sire": null,
      "dam": null,
      "dam_sire": null,
      "honmei_score": 0.0182,
      "ev_score": 2.0082,
      "kelly_fraction": null,
      "manji_ev": null,
      "odds_vs_morning": null,
      "odds_velocity": null
    },
    {
      "rank": 4,
      "gate_number": 8,
      "horse_number": 9,
      "horse_name": "ペイシャフラワー",
      "horse_id": null,
      "sex_age": "牝4",
      "weight_carried": 55.0,
      "jockey": "団野",
      "trainer": "栗東高橋康",
      "finish_time": "1:21.7",
      "margin": "1/2",
      "win_odds": 14.5,
      "popularity": 6,
      "horse_weight": 470,
      "horse_weight_diff": -2,
      "sire": null,
      "dam": null,
      "dam_sire": null,
      "honmei_score": 0.0153,
      "ev_score": 0.0,
      "kelly_fraction": null,
      "manji_ev": null,
      "odds_vs_morning": null,
      "odds_velocity": null
    },
    {
      "rank": 5,
      "gate_number": 3,
      "horse_number": 3,
      "horse_name": "ピラティス",
      "horse_id": null,
      "sex_age": "牝5",
      "weight_carried": 53.0,
      "jockey": "▲今村",
      "trainer": "栗東松永幹",
      "finish_time": "1:21.9",
      "margin": "1.1/4",
      "win_odds": 46.7,
      "popularity": 9,
      "horse_weight": 460,
      "horse_weight_diff": 0,
      "sire": null,
      "dam": null,
      "dam_sire": null,
      "honmei_score": 0.0162,
      "ev_score": 0.0,
      "kelly_fraction": null,
      "manji_ev": null,
      "odds_vs_morning": null,
      "odds_velocity": null
    },
    {
      "rank": 6,
      "gate_number": 7,
      "horse_number": 8,
      "horse_name": "ヴァンルーラー",
      "horse_id": null,
      "sex_age": "牝5",
      "weight_carried": 56.0,
      "jockey": "池添",
      "trainer": "栗東吉岡",
      "finish_time": "1:22.0",
      "margin": "クビ",
      "win_odds": 39.3,
      "popularity": 8,
      "horse_weight": 466,
      "horse_weight_diff": 0,
      "sire": null,
      "dam": null,
      "dam_sire": null,
      "honmei_score": 0.033,
      "ev_score": 1.3837,
      "kelly_fraction": null,
      "manji_ev": null,
      "odds_vs_morning": null,
      "odds_velocity": null
    },
    {
      "rank": 7,
      "gate_number": 4,
      "horse_number": 4,
      "horse_name": "ウォータールグラン",
      "horse_id": null,
      "sex_age": "牝5",
      "weight_carried": 56.0,
      "jockey": "菅原明",
      "trainer": "栗東河内",
      "finish_time": "1:22.0",
      "margin": "クビ",
      "win_odds": 19.9,
      "popularity": 7,
      "horse_weight": 508,
      "horse_weight_diff": 12,
      "sire": null,
      "dam": null,
      "dam_sire": null,
      "honmei_score": 0.0117,
      "ev_score": 0.0,
      "kelly_fraction": null,
      "manji_ev": null,
      "odds_vs_morning": null,
      "odds_velocity": null
    },
    {
      "rank": 8,
      "gate_number": 6,
      "horse_number": 6,
      "horse_name": "ショウナンナダル",
      "horse_id": null,
      "sex_age": "牝5",
      "weight_carried": 54.0,
      "jockey": "△田口",
      "trainer": "栗東須貝",
      "finish_time": "1:22.2",
      "margin": "1.1/4",
      "win_odds": 12.4,
      "popularity": 5,
      "horse_weight": 456,
      "horse_weight_diff": 0,
      "sire": null,
      "dam": null,
      "dam_sire": null,
      "honmei_score": 0.0628,
      "ev_score": 0.0,
      "kelly_fraction": null,
      "manji_ev": null,
      "odds_vs_morning": null,
      "odds_velocity": null
    },
    {
      "rank": 9,
      "gate_number": 7,
      "horse_number": 7,
      "horse_name": "ルクスドヌーヴ",
      "horse_id": null,
      "sex_age": "牝4",
      "weight_carried": 55.0,
      "jockey": "武豊",
      "trainer": "栗東須貝",
      "finish_time": "1:22.4",
      "margin": "1",
      "win_odds": 7.4,
      "popularity": 4,
      "horse_weight": 452,
      "horse_weight_diff": 0,
      "sire": null,
      "dam": null,
      "dam_sire": null,
      "honmei_score": 0.0143,
      "ev_score": 0.0,
      "kelly_fraction": null,
      "manji_ev": null,
      "odds_vs_morning": null,
      "odds_velocity": null
    },
    {
      "rank": 10,
      "gate_number": 2,
      "horse_number": 2,
      "horse_name": "ハッピーオーサム",
      "horse_id": null,
      "sex_age": "牝6",
      "weight_carried": 55.0,
      "jockey": "☆角田河",
      "trainer": "栗東藤原",
      "finish_time": "1:22.5",
      "margin": "3/4",
      "win_odds": 62.3,
      "popularity": 10,
      "horse_weight": 506,
      "horse_weight_diff": 6,
      "sire": null,
      "dam": null,
      "dam_sire": null,
      "honmei_score": 0.0289,
      "ev_score": 1.9863,
      "kelly_fraction": null,
      "manji_ev": null,
      "odds_vs_morning": null,
      "odds_velocity": null
    }
  ],
  "payouts": [
    {
      "bet_type": "単勝",
      "combination": "1",
      "payout": 510,
      "popularity": 3
    },
    {
      "bet_type": "複勝",
      "combination": "10",
      "payout": 120,
      "popularity": 1
    },
    {
      "bet_type": "複勝",
      "combination": "5",
      "payout": 140,
      "popularity": 2
    },
    {
      "bet_type": "複勝",
      "combination": "1",
      "payout": 150,
      "popularity": 3
    },
    {
      "bet_type": "枠連",
      "combination": "1-8",
      "payout": 520,
      "popularity": 2
    },
    {
      "bet_type": "馬連",
      "combination": "1-10",
      "payout": 600,
      "popularity": 2
    },
    {
      "bet_type": "ワイド",
      "combination": "1-10",
      "payout": 230,
      "popularity": 1
    },
    {
      "bet_type": "ワイド",
      "combination": "5-10",
      "payout": 250,
      "popularity": 2
    },
    {
      "bet_type": "ワイド",
      "combination": "1-5",
      "payout": 410,
      "popularity": 4
    },
    {
      "bet_type": "馬単",
      "combination": "1→10",
      "payout": 1360,
      "popularity": 4
    },
    {
      "bet_type": "三連複",
      "combination": "1-5-10",
      "payout": 760,
      "popularity": 1
    },
    {
      "bet_type": "三連単",
      "combination": "1→10→5",
      "payout": 4870,
      "popularity": 8
    }
  ],
  "predictions": [],
  "training_evals": {},
  "prerace": {
    "bias": {},
    "ev_recommend": [],
    "generated_at": "2026-04-08T21:34:27.535769"
  }
}