{
  "race_id": "202405050707",
  "race_name": "",
  "date": "2024-11-23",
  "venue": "東京",
  "race_number": 7,
  "distance": 0,
  "surface": "",
  "track_direction": "",
  "weather": "",
  "condition": "",
  "year": "2024",
  "results": [
    {
      "rank": null,
      "gate_number": 1,
      "horse_number": 1,
      "horse_name": "ズイウンゴサイ",
      "horse_id": "2021100597",
      "sex_age": "牡7",
      "weight_carried": 56.0,
      "jockey": "丸田恭介",
      "trainer": "武市康男",
      "finish_time": null,
      "margin": null,
      "win_odds": null,
      "popularity": null,
      "horse_weight": null,
      "horse_weight_diff": null,
      "sire": "シュヴァルグラン",
      "dam": "ブルーインザスカイ",
      "dam_sire": "チチカステナンゴChichicastenango(仏)"
    },
    {
      "rank": null,
      "gate_number": 2,
      "horse_number": 2,
      "horse_name": "エラン",
      "horse_id": "2021105453",
      "sex_age": "牡4",
      "weight_carried": 56.0,
      "jockey": "ムーア",
      "trainer": "蛯名正義",
      "finish_time": null,
      "margin": null,
      "win_odds": null,
      "popularity": null,
      "horse_weight": null,
      "horse_weight_diff": null,
      "sire": "ラブリーデイ",
      "dam": "オーキッドレイ",
      "dam_sire": "ディープインパクト"
    },
    {
      "rank": null,
      "gate_number": 3,
      "horse_number": 3,
      "horse_name": "ビートザレコード",
      "horse_id": "2019104588",
      "sex_age": "牡3",
      "weight_carried": 58.0,
      "jockey": "吉田豊",
      "trainer": "戸田博文",
      "finish_time": null,
      "margin": null,
      "win_odds": null,
      "popularity": null,
      "horse_weight": null,
      "horse_weight_diff": null,
      "sire": "ジャスタウェイ",
      "dam": "ビートリックスキッドBeatrix Kiddo(仏)",
      "dam_sire": "Victory Note"
    },
    {
      "rank": null,
      "gate_number": 4,
      "horse_number": 4,
      "horse_name": "ミッキーストライク",
      "horse_id": "2021105729",
      "sex_age": "牡3",
      "weight_carried": 56.0,
      "jockey": "坂井瑠星",
      "trainer": "矢作芳人",
      "finish_time": null,
      "margin": null,
      "win_odds": null,
      "popularity": null,
      "horse_weight": null,
      "horse_weight_diff": null,
      "sire": "ドゥラメンテ",
      "dam": "フォンタネリーチェFontanelice(愛)",
      "dam_sire": "Vale of York"
    },
    {
      "rank": null,
      "gate_number": 5,
      "horse_number": 5,
      "horse_name": "ピースヒロフェイス",
      "horse_id": "2021105769",
      "sex_age": "牝3",
      "weight_carried": 54.0,
      "jockey": "石橋脩",
      "trainer": "牧光二",
      "finish_time": null,
      "margin": null,
      "win_odds": null,
      "popularity": null,
      "horse_weight": null,
      "horse_weight_diff": null,
      "sire": "サトノダイヤモンド",
      "dam": "ペルヴィアンリリー",
      "dam_sire": "フレンチデピュティFrench Deputy(米)"
    },
    {
      "rank": null,
      "gate_number": 5,
      "horse_number": 6,
      "horse_name": "テイクノーティス",
      "horse_id": "2021104776",
      "sex_age": "牡4",
      "weight_carried": 56.0,
      "jockey": "荻野極",
      "trainer": "伊坂重信",
      "finish_time": null,
      "margin": null,
      "win_odds": null,
      "popularity": null,
      "horse_weight": null,
      "horse_weight_diff": null,
      "sire": "ハービンジャーHarbinger(英)",
      "dam": "ハイヤーアプシス",
      "dam_sire": "ダノンシャンティ"
    },
    {
      "rank": null,
      "gate_number": 6,
      "horse_number": 7,
      "horse_name": "イクリール",
      "horse_id": "2021106563",
      "sex_age": "牡1",
      "weight_carried": 56.0,
      "jockey": "丸山元気",
      "trainer": "青木孝文",
      "finish_time": null,
      "margin": null,
      "win_odds": null,
      "popularity": null,
      "horse_weight": null,
      "horse_weight_diff": null,
      "sire": "シュヴァルグラン",
      "dam": "エンプレスティアラ",
      "dam_sire": "クロフネ"
    },
    {
      "rank": null,
      "gate_number": 6,
      "horse_number": 8,
      "horse_name": "コンテソレーラ",
      "horse_id": "2021105449",
      "sex_age": "牝3",
      "weight_carried": 54.0,
      "jockey": "石川裕紀",
      "trainer": "手塚貴久",
      "finish_time": null,
      "margin": null,
      "win_odds": null,
      "popularity": null,
      "horse_weight": null,
      "horse_weight_diff": null,
      "sire": "リアルスティール",
      "dam": "エレクトラムElektrum(愛)",
      "dam_sire": "High Chaparral(愛)"
    },
    {
      "rank": null,
      "gate_number": 7,
      "horse_number": 9,
      "horse_name": "マイネルジャッカル",
      "horse_id": "2018106739",
      "sex_age": "牡3",
      "weight_carried": 58.0,
      "jockey": "丹内祐次",
      "trainer": "西田雄一",
      "finish_time": null,
      "margin": null,
      "win_odds": null,
      "popularity": null,
      "horse_weight": null,
      "horse_weight_diff": null,
      "sire": "トーホウジャッカル",
      "dam": "リトルラブソング",
      "dam_sire": "マイネルラヴ"
    },
    {
      "rank": null,
      "gate_number": 7,
      "horse_number": 10,
      "horse_name": "トラストボス",
      "horse_id": "2021106972",
      "sex_age": "牡3",
      "weight_carried": 56.0,
      "jockey": "戸崎圭太",
      "trainer": "高橋文雅",
      "finish_time": null,
      "margin": null,
      "win_odds": null,
      "popularity": null,
      "horse_weight": null,
      "horse_weight_diff": null,
      "sire": "キズナ",
      "dam": "ウェストレー",
      "dam_sire": "オルフェーヴル"
    },
    {
      "rank": null,
      "gate_number": 8,
      "horse_number": 11,
      "horse_name": "ダノンホイットニー",
      "horse_id": "2021105639",
      "sex_age": "牝3",
      "weight_carried": 54.0,
      "jockey": "ルメール",
      "trainer": "大竹正博",
      "finish_time": null,
      "margin": null,
      "win_odds": null,
      "popularity": null,
      "horse_weight": null,
      "horse_weight_diff": null,
      "sire": "ミッキーロケット",
      "dam": "ダノンチェリー",
      "dam_sire": "ディープインパクト"
    },
    {
      "rank": null,
      "gate_number": 8,
      "horse_number": 12,
      "horse_name": "ポルトフェリス",
      "horse_id": "2021105780",
      "sex_age": "牝4",
      "weight_carried": 54.0,
      "jockey": "ドイル",
      "trainer": "栗田徹",
      "finish_time": null,
      "margin": null,
      "win_odds": null,
      "popularity": null,
      "horse_weight": null,
      "horse_weight_diff": null,
      "sire": "エピファネイア",
      "dam": "ポルトフィーノ",
      "dam_sire": "クロフネ"
    }
  ],
  "payouts": [],
  "predictions": [],
  "training_evals": {}
}